README.rst
setup.py
tests/__init__.py
tests/_test_for_func_loading.py
tests/test_client.py
tests/test_compact.py
tests/test_const.py
tests/test_crypt.py
tests/test_database.py
tests/test_extractor.py
tests/test_func_loading.py
tests/test_funclibs.py
tests/test_h_funcs.py
tests/test_json.py
tests/test_m_funcs.py
tests/test_preprocessing_pipeline.py
tests/test_r_funcs.py
tests/test_random.py
velenxc/__init__.py
velenxc/compat.py
velenxc/const.py
velenxc/errors.py
velenxc/random.py
velenxc.egg-info/PKG-INFO
velenxc.egg-info/SOURCES.txt
velenxc.egg-info/dependency_links.txt
velenxc.egg-info/requires.txt
velenxc.egg-info/top_level.txt
velenxc/funclibs/__init__.py
velenxc/funclibs/f.py
velenxc/funclibs/f_assert.py
velenxc/funclibs/h.py
velenxc/funclibs/m.py
velenxc/funclibs/r.py
velenxc/parsers/__init__.py
velenxc/parsers/json.py
velenxc/preprocessing/__init__.py
velenxc/preprocessing/extract.py
velenxc/preprocessing/pipeline.py
velenxc/utils/__init__.py
velenxc/utils/client.py
velenxc/utils/crypto.py