Metadata-Version: 1.1
Name: velenxc
Version: 0.1.20171107163220
Summary: Machine Learning utility lib
Home-page: https://pypi.python.org/pypi/velenxc
Author: digcreditdev
Author-email: niushaohan@digcredit.com
License: MIT
Platform: UNKNOWN
Classifier: Environment :: Web Environment
Classifier: Intended Audience :: Developers
Classifier: Operating System :: OS Independent
Classifier: Topic :: Utilities
Classifier: Topic :: Software Development :: Libraries :: Python Modules
Classifier: Programming Language :: Python
Classifier: Programming Language :: Python :: 3
Classifier: Programming Language :: Python :: 3.5
Classifier: Programming Language :: Python :: 3.6
